video_compressing/__init__.py
video_compressing/helper.py
video_compressing/reduce_video.py
video_compressing/tools.py
video_compressing-0.1.4.dist-info/METADATA
video_compressing-0.1.4.dist-info/WHEEL
video_compressing-0.1.4.dist-info/RECORD
