Metadata-Version: 2.1
Name: video_compressing
Version: 0.1.4
Summary: Package to compress multiple large .MOV or .MP4 videos into a single light .mp4 video.
Home-page: https://github.com/Gabriel-melki/video_compressing
Author: gabriel-melki
Requires-Python: >=3.12.0,<4.0.0
Classifier: Programming Language :: Python :: 3
Classifier: Programming Language :: Python :: 3.12
Classifier: Programming Language :: Python :: 3.13
Requires-Dist: ffmpeg-python (>=0.2.0,<0.3.0)
Requires-Dist: numpy (>=2.1.3,<3.0.0)
Requires-Dist: requests (>=2.32.3,<3.0.0)
Requires-Dist: subprocess32 (>=3.5.4,<4.0.0)
Requires-Dist: tqdm (>=4.63.0,<5.0.0)
Project-URL: Documentation, https://github.com/Gabriel-melki/video_compressing#readme
Project-URL: Repository, https://github.com/Gabriel-melki/video_compressing
